pysail/__init__.py
pysail/__main__.py
pysail/_native.pypy39-pp73-aarch64-linux-gnu.so
pysail/cli.py
pysail/data/compatibility/catalog.json
pysail/data/compatibility/column.json
pysail/data/compatibility/dataframe.json
pysail/data/compatibility/functions/aggregate.json
pysail/data/compatibility/functions/generator.json
pysail/data/compatibility/functions/scalar/array.json
pysail/data/compatibility/functions/scalar/bitwise.json
pysail/data/compatibility/functions/scalar/collection.json
pysail/data/compatibility/functions/scalar/conditional.json
pysail/data/compatibility/functions/scalar/conversion.json
pysail/data/compatibility/functions/scalar/csv.json
pysail/data/compatibility/functions/scalar/datetime.json
pysail/data/compatibility/functions/scalar/hash.json
pysail/data/compatibility/functions/scalar/json.json
pysail/data/compatibility/functions/scalar/map.json
pysail/data/compatibility/functions/scalar/math.json
pysail/data/compatibility/functions/scalar/misc.json
pysail/data/compatibility/functions/scalar/normal.json
pysail/data/compatibility/functions/scalar/predicate.json
pysail/data/compatibility/functions/scalar/sort.json
pysail/data/compatibility/functions/scalar/string.json
pysail/data/compatibility/functions/scalar/struct.json
pysail/data/compatibility/functions/scalar/udf_udtf_udt.json
pysail/data/compatibility/functions/scalar/url.json
pysail/data/compatibility/functions/scalar/variant.json
pysail/data/compatibility/functions/scalar/xml.json
pysail/data/compatibility/functions/window.json
pysail/data/compatibility/sparksession.json
pysail/data/compatibility/structtype.json
pysail/data/tpcds/queries/q1.sql
pysail/data/tpcds/queries/q10.sql
pysail/data/tpcds/queries/q11.sql
pysail/data/tpcds/queries/q12.sql
pysail/data/tpcds/queries/q13.sql
pysail/data/tpcds/queries/q14.sql
pysail/data/tpcds/queries/q15.sql
pysail/data/tpcds/queries/q16.sql
pysail/data/tpcds/queries/q17.sql
pysail/data/tpcds/queries/q18.sql
pysail/data/tpcds/queries/q19.sql
pysail-0.4.6.dist-info/METADATA
pysail-0.4.6.dist-info/WHEEL
pysail-0.4.6.dist-info/entry_points.txt
pysail-0.4.6.dist-info/licenses/LICENSE
pysail-0.4.6.dist-info/RECORD
