Metadata-Version: 2.4
Name: pysail
Version: 0.4.6
Classifier: Development Status :: 4 - Beta
Classifier: Environment :: Console
Classifier: Intended Audience :: Developers
Classifier: Intended Audience :: Science/Research
Classifier: License :: OSI Approved :: Apache Software License
Classifier: Operating System :: OS Independent
Classifier: Programming Language :: Python
Classifier: Programming Language :: Python :: 3
Classifier: Programming Language :: Python :: 3 :: Only
Classifier: Programming Language :: Python :: 3.9
Classifier: Programming Language :: Python :: 3.10
Classifier: Programming Language :: Python :: 3.11
Classifier: Programming Language :: Python :: 3.12
Classifier: Programming Language :: Python :: 3.13
Classifier: Programming Language :: Python :: 3.14
Classifier: Programming Language :: Rust
Classifier: Topic :: Scientific/Engineering
Requires-Dist: mcp>=1.0.0,<2 ; extra == 'mcp'
Requires-Dist: pyspark-client>=4.0,!=4.1.0,<4.2 ; extra == 'test'
Requires-Dist: duckdb>=1.0,<2 ; extra == 'test'
Requires-Dist: pytest>=8.4,<9 ; extra == 'test'
Requires-Dist: pytest-bdd>=8.1,<9 ; extra == 'test'
Requires-Dist: syrupy>=5.0,<6 ; extra == 'test'
Requires-Dist: jinja2>=3.1,<4 ; extra == 'test'
Requires-Dist: pillow>=10.3.0,<11 ; extra == 'test'
Requires-Dist: pyiceberg[sql-sqlite,pyiceberg-core]==0.10.0 ; extra == 'test'
Requires-Dist: pydantic>=2.11,<2.12 ; extra == 'test'
Requires-Dist: jedi>=0.19.2,<0.20 ; extra == 'test'
Requires-Dist: jsonpath-ng>=1.6,<2 ; extra == 'test'
Requires-Dist: pyyaml>=6.0,<7 ; extra == 'test'
Provides-Extra: mcp
Provides-Extra: test
License-File: LICENSE
Summary: Sail Python library
Keywords: data,big data,sql,spark,pyspark,arrow,datafusion
Author-email: LakeSail <hello@lakesail.com>
Requires-Python: >=3.9, <3.15
Project-URL: Documentation, https://docs.lakesail.com/sail/latest/
Project-URL: Homepage, https://lakesail.com
Project-URL: Issues, https://github.com/lakehq/sail/issues
Project-URL: Repository, https://github.com/lakehq/sail
